LICENSE
crudadmin/__init__.py
crudadmin/py.typed
crudadmin/admin_interface/__init__.py
crudadmin/admin_interface/admin_site.py
crudadmin/admin_interface/auth.py
crudadmin/admin_interface/crud_admin.py
crudadmin/admin_interface/helper.py
crudadmin/admin_interface/model_view.py
crudadmin/admin_interface/typing.py
crudadmin/admin_interface/middleware/__init__.py
crudadmin/admin_interface/middleware/auth.py
crudadmin/admin_interface/middleware/https.py
crudadmin/admin_interface/middleware/ip_restriction.py
crudadmin/admin_user/__init__.py
crudadmin/admin_user/models.py
crudadmin/admin_user/schemas.py
crudadmin/admin_user/service.py
crudadmin/core/__init__.py
crudadmin/core/auth.py
crudadmin/core/db.py
crudadmin/core/exceptions.py
crudadmin/core/rate_limiter.py
crudadmin/core/schemas/__init__.py
crudadmin/core/schemas/timestamp.py
crudadmin/event/__init__.py
crudadmin/event/decorators.py
crudadmin/event/integration.py
crudadmin/event/models.py
crudadmin/event/schemas.py
crudadmin/event/service.py
crudadmin/session/__init__.py
crudadmin/session/configs.py
crudadmin/session/manager.py
crudadmin/session/models.py
crudadmin/session/schemas.py
crudadmin/session/storage.py
crudadmin/session/user_agents_types.py
crudadmin/session/backends/__init__.py
crudadmin/session/backends/database.py
crudadmin/session/backends/hybrid.py
crudadmin/session/backends/memcached.py
crudadmin/session/backends/memory.py
crudadmin/session/backends/redis.py
crudadmin/static/favicon.png
crudadmin/static/htmx.min.js
crudadmin/templates/admin/dashboard/dashboard.html
crudadmin/templates/admin/dashboard/dashboard_content.html
crudadmin/templates/admin/management/events.html
crudadmin/templates/admin/management/events_content.html
crudadmin/templates/admin/management/health.html
crudadmin/templates/admin/management/health_content.html
crudadmin/templates/admin/model/create.html
crudadmin/templates/admin/model/list.html
crudadmin/templates/admin/model/update.html
crudadmin-0.4.3.dist-info/METADATA
crudadmin-0.4.3.dist-info/WHEEL
crudadmin-0.4.3.dist-info/licenses/LICENSE
crudadmin-0.4.3.dist-info/RECORD
