Metadata-Version: 2.4
Name: crudadmin
Version: 0.4.3
Summary: FastAPI-based admin interface with authentication, event logging and CRUD operations
Project-URL: Homepage, https://github.com/benavlabs/crudadmin
Project-URL: Documentation, https://benavlabs.github.io/crudadmin
Project-URL: Repository, https://github.com/benavlabs/crudadmin
Project-URL: Issues, https://github.com/benavlabs/crudadmin/issues
Project-URL: Changelog, https://github.com/benavlabs/crudadmin/releases
Author-email: Igor Benav <igor.magalhaes.r@gmail.com>
License-File: LICENSE
Classifier: Development Status :: 3 - Alpha
Classifier: Environment :: Web Environment
Classifier: Framework :: FastAPI
Classifier: Framework :: Pydantic
Classifier: Framework :: Pydantic :: 2
Classifier: Intended Audience :: Developers
Classifier: License :: OSI Approved :: MIT License
Classifier: Operating System :: OS Independent
Classifier: Programming Language :: Python :: 3
Classifier: Programming Language :: Python :: 3 :: Only
Classifier: Programming Language :: Python :: 3.9
Classifier: Programming Language :: Python :: 3.10
Classifier: Programming Language :: Python :: 3.11
Classifier: Programming Language :: Python :: 3.12
Classifier: Topic :: Internet :: WWW/HTTP
Classifier: Topic :: Internet :: WWW/HTTP :: HTTP Servers
Classifier: Topic :: Software Development :: Libraries :: Application Frameworks
Classifier: Typing :: Typed
Requires-Python: >=3.9.2
Requires-Dist: aiosqlite>=0.20.0
Requires-Dist: bcrypt>=4.2.1
Requires-Dist: fastapi>=0.115.6
Requires-Dist: fastcrud>=0.15.12
Requires-Dist: greenlet>=3.1.1
Requires-Dist: jinja2>=3.1.5
Requires-Dist: pydantic-settings>=2.6.1
Requires-Dist: pydantic[email]>=2.10.4
Requires-Dist: python-jose>=3.3.0
Requires-Dist: python-multipart>=0.0.20
Requires-Dist: sqlalchemy>=2.0.36
Requires-Dist: user-agents>=2.2.0
Provides-Extra: all
Requires-Dist: httptools>=0.6.4; extra == 'all'
Requires-Dist: httpx>=0.28.1; extra == 'all'
Requires-Dist: mkdocs-material>=9.6.1; extra == 'all'
Requires-Dist: mkdocs-meta-descriptions-plugin>=4.0.0; extra == 'all'
Requires-Dist: mkdocs>=1.6.1; extra == 'all'
Requires-Dist: mkdocstrings[python]>=0.27.0; extra == 'all'
Requires-Dist: mypy>=1.9.0; extra == 'all'
Requires-Dist: pre-commit>=3.5.0; extra == 'all'
Requires-Dist: pytest-asyncio>=0.25.3; extra == 'all'
Requires-Dist: pytest>=8.3.4; extra == 'all'
Requires-Dist: ruff>=0.9.3; extra == 'all'
Requires-Dist: sqlalchemy-utils>=0.41.2; extra == 'all'
Requires-Dist: sqlalchemy[mypy]>=2.0.36; extra == 'all'
Requires-Dist: testcontainers[postgresql]>=4.9.1; extra == 'all'
Requires-Dist: uvicorn[standard]>=0.12.0; extra == 'all'
Provides-Extra: dev
Requires-Dist: httptools>=0.6.4; extra == 'dev'
Requires-Dist: httpx>=0.28.1; extra == 'dev'
Requires-Dist: mypy>=1.9.0; extra == 'dev'
Requires-Dist: pre-commit>=3.5.0; extra == 'dev'
Requires-Dist: pytest-asyncio>=0.25.3; extra == 'dev'
Requires-Dist: pytest>=8.3.4; extra == 'dev'
Requires-Dist: ruff>=0.9.3; extra == 'dev'
Requires-Dist: sqlalchemy-utils>=0.41.2; extra == 'dev'
Requires-Dist: sqlalchemy[mypy]>=2.0.36; extra == 'dev'
Requires-Dist: testcontainers[postgresql]>=4.9.1; extra == 'dev'
Provides-Extra: docs
Requires-Dist: mkdocs-material>=9.6.1; extra == 'docs'
Requires-Dist: mkdocs-meta-descriptions-plugin>=4.0.0; extra == 'docs'
Requires-Dist: mkdocs>=1.6.1; extra == 'docs'
Requires-Dist: mkdocstrings[python]>=0.27.0; extra == 'docs'
Provides-Extra: memcached
Requires-Dist: aiomcache>=0.8.2; extra == 'memcached'
Provides-Extra: mysql
Requires-Dist: aiomysql>=0.2.0; extra == 'mysql'
Provides-Extra: postgres
Requires-Dist: asyncpg>=0.29.0; extra == 'postgres'
Provides-Extra: redis
Requires-Dist: redis>=6.2.0; extra == 'redis'
Provides-Extra: standard
Requires-Dist: uvicorn[standard]>=0.12.0; extra == 'standard'
Provides-Extra: test
Requires-Dist: aiomcache>=0.8.2; extra == 'test'
Requires-Dist: redis>=6.2.0; extra == 'test'
